vantiqservicesdk.py
vantiqservicesdk-0.2.2.dist-info/licenses/LICENSE
vantiqservicesdk-0.2.2.dist-info/METADATA
vantiqservicesdk-0.2.2.dist-info/WHEEL
vantiqservicesdk-0.2.2.dist-info/top_level.txt
vantiqservicesdk-0.2.2.dist-info/RECORD
