Metadata-Version: 2.4
Name: vantiqservicesdk
Version: 0.2.2
Summary: SDK for building Vantiq service connectors in Python
Author-email: Vantiq <sfitts@vantiq.com>
License: MIT
Project-URL: Homepage, https://github.com/Vantiq/vantiq-service-connectors
Classifier: Development Status :: 4 - Beta
Classifier: License :: OSI Approved :: MIT License
Classifier: Programming Language :: Python :: 3.9
Classifier: Programming Language :: Python :: 3.10
Classifier: Programming Language :: Python :: 3.11
Classifier: Programming Language :: Python :: 3.12
Requires-Python: >=3.9
License-File: LICENSE
Requires-Dist: fastapi
Requires-Dist: uvicorn[standard]
Requires-Dist: vantiqsdk
Requires-Dist: prometheus-client
Dynamic: license-file
